test/__init__.py
test/test.py
tmple/__init__.py
tmple/generator.py
tmple/main.py
tmple/recipe.py
tmple/template.py
tmple/utils.py
tmple-0.1.0.dist-info/LICENSE
tmple-0.1.0.dist-info/METADATA
tmple-0.1.0.dist-info/WHEEL
tmple-0.1.0.dist-info/entry_points.txt
tmple-0.1.0.dist-info/top_level.txt
tmple-0.1.0.dist-info/RECORD
