Metadata-Version: 2.1
Name: tmple
Version: 0.1.0
Summary: General files or content generator, using template and data/variables.
Home-page: https://github.com/maztohir/tmple
Author: Muhamad Tohir
Author-email: maztohir@gmail.com
License: UNKNOWN
Project-URL: Bug Tracker, https://github.com/maztohir/tmple/issues
Platform: UNKNOWN
Classifier: Programming Language :: Python :: 3
Classifier: License :: OSI Approved :: MIT License
Classifier: Operating System :: OS Independent
Classifier: Topic :: Software Development :: Code Generators
Requires-Python: >=3.6
Requires-Dist: Jinja2 (==2.11.2)
Requires-Dist: markupsafe (==2.0.1)
Requires-Dist: PyYAML (==5.4.1)
